emp/__init__.py
emp/emp_ide.py
emp/emp_utils.py
emp/emp_webide.py
emp/emp_wifi.py
emp_ide_ext-0.0.1.dev21.dist-info/AUTHORS
emp_ide_ext-0.0.1.dev21.dist-info/LICENSE
emp_ide_ext-0.0.1.dev21.dist-info/METADATA
emp_ide_ext-0.0.1.dev21.dist-info/WHEEL
emp_ide_ext-0.0.1.dev21.dist-info/pbr.json
emp_ide_ext-0.0.1.dev21.dist-info/top_level.txt
emp_ide_ext-0.0.1.dev21.dist-info/RECORD
