Metadata-Version: 2.1
Name: emp-ide-ext
Version: 0.0.1.dev21
Summary: EMP-IDE micropython extension module
Home-page: https://github.com/EasyMicroPython/EMP-EXT
Author: singein
Author-email: singein@outlook.com
License: MIT
Platform: UNKNOWN
